tests/__init__.py
tests/test_hashtag.py
tiktok_hashtag_collector/__init__.py
tiktok_hashtag_collector/hashtag.py
tiktok_hashtag_collector-0.1.2.dist-info/LICENSE
tiktok_hashtag_collector-0.1.2.dist-info/METADATA
tiktok_hashtag_collector-0.1.2.dist-info/WHEEL
tiktok_hashtag_collector-0.1.2.dist-info/top_level.txt
tiktok_hashtag_collector-0.1.2.dist-info/RECORD
