Metadata-Version: 2.1
Name: tiktok-hashtag-collector
Version: 0.1.2
Summary: A package to collect TikTok posts by hashtag
Home-page: https://github.com/donghoanghiip/tiktok-hashtag-collector
Author: Hiip
Author-email: dong.hoang@hiip.asia
License: UNKNOWN
Platform: UNKNOWN
Classifier: Programming Language :: Python :: 3
Classifier: License :: OSI Approved :: MIT License
Classifier: Operating System :: OS Independent
Requires-Python: >=3.6
License-File: LICENSE
Requires-Dist: requests>=2.25.0
Requires-Dist: pandas>=1.2.0
Requires-Dist: boto3>=1.26.0
